accelbyte_py_sdk/api/gdpr/__init__.py
accelbyte_py_sdk/api/gdpr/errors.py
accelbyte_py_sdk/api/gdpr/models/__init__.py
accelbyte_py_sdk/api/gdpr/models/dto_extend_config_dto.py
accelbyte_py_sdk/api/gdpr/models/dto_finished_data_deletion.py
accelbyte_py_sdk/api/gdpr/models/dto_finished_data_request.py
accelbyte_py_sdk/api/gdpr/models/dto_list_finished_data_deletion.py
accelbyte_py_sdk/api/gdpr/models/dto_list_finished_data_requests.py
accelbyte_py_sdk/api/gdpr/models/dto_platform_account_closure_client_request.py
accelbyte_py_sdk/api/gdpr/models/dto_platform_account_closure_client_response.py
accelbyte_py_sdk/api/gdpr/models/dto_platform_account_closure_clients_response.py
accelbyte_py_sdk/api/gdpr/models/dto_platform_account_closure_mock_request.py
accelbyte_py_sdk/api/gdpr/models/dto_s2s_data_request_summary.py
accelbyte_py_sdk/api/gdpr/models/dto_service_config_dto.py
accelbyte_py_sdk/api/gdpr/models/dto_service_configuration_dto.py
accelbyte_py_sdk/api/gdpr/models/dto_service_configuration_update_request.py
accelbyte_py_sdk/api/gdpr/models/dto_services_configuration_response.py
accelbyte_py_sdk/api/gdpr/models/dto_user_platform_account_closure_histories_response.py
accelbyte_py_sdk/api/gdpr/models/dto_user_platform_account_closure_history.py
accelbyte_py_sdk/api/gdpr/models/dto_xbox_bp_cert_validation_request.py
accelbyte_py_sdk/api/gdpr/models/dto_xbox_bp_cert_validation_response.py
accelbyte_py_sdk/api/gdpr/models/models_data_retrieval_response.py
accelbyte_py_sdk/api/gdpr/models/models_deletion_data.py
accelbyte_py_sdk/api/gdpr/models/models_deletion_status.py
accelbyte_py_sdk/api/gdpr/models/models_list_deletion_data_response.py
accelbyte_py_sdk/api/gdpr/models/models_list_personal_data_response.py
accelbyte_py_sdk/api/gdpr/models/models_pagination.py
accelbyte_py_sdk/api/gdpr/models/models_personal_data.py
accelbyte_py_sdk/api/gdpr/models/models_request_delete_response.py
accelbyte_py_sdk/api/gdpr/models/models_s2s_data_retrieval_response.py
accelbyte_py_sdk_service_gdpr-0.23.0.dist-info/METADATA
accelbyte_py_sdk_service_gdpr-0.23.0.dist-info/WHEEL
accelbyte_py_sdk_service_gdpr-0.23.0.dist-info/top_level.txt
accelbyte_py_sdk_service_gdpr-0.23.0.dist-info/RECORD
