Metadata-Version: 2.4
Name: accelbyte-py-sdk-service-gdpr
Version: 0.23.0
Summary: AccelByte Python SDK - AccelByte Gaming Services Gdpr Service
Requires-Python: >=3.9
Requires-Dist: accelbyte-py-sdk-core
